{
    "catalog-tag": "RIT:BBH:0482",
    "resolution-tag": "n120",
    "id-tag": "id1",
    "run-name": "D12.50_q0.6000_a0.80_0.80_opt2_n120",
    "data-type": "NR",
    "system-type": "Aligned",
    "comments": "none",
    "authors-emails": "JamesHealy<jchsma@rit.edu>,CarlosLousto<colsma@rit.edu>",
    "simulation-bibtex-keys": "",
    "code-bibtex-keys": "Campanelli:2005dd",
    "initial-data-bibtex-keys": "Bowen:1980yu,Brandt:1997tf,Ansorg:2004ds",
    "quasicircular-bibtex-keys": "Husa:2007rh,Buonanno:2010yk,Healy:2017zqj",
    "eccentricity-bibtex-keys": "Campanelli:2008nk",
    "extrapolation-bibtex-keys": "Nakano:2015pta",
    "code": "LazEv",
    "evolution-system": "BSSN",
    "evolution-gauge": "1+log/Gamma-driver(eta=2.0)",
    "cfl": "0.333333333333333",
    "fd-order": "6",
    "dissipation-order": "5",
    "eccentricity-measurement-method": "r^2-rddot",
    "eccentricity": "0.0009932749",
    "freq-start-22": "0.006650922351982",
    "freq-start-22-Hz-1Msun": "1349.964192783031649",
    "number-of-cycles-22": "",
    "number-of-orbits": "16.4601605282188",
    "initial-data-type": "Bowen-Yorkquasicircular",
    "initial-ADM-energy": "0.991880460230673",
    "initial-orbital-angular-momentum": "0.931785530086975",
    "initial-ADM-angular-momentum-x": "0",
    "initial-ADM-angular-momentum-y": "0",
    "initial-ADM-angular-momentum-z": "1.35678553008697",
    "initial-separation": "12.5",
    "initial-mass1": "0.375",
    "initial-mass2": "0.625",
    "initial-total-mass": "1",
    "initial-bh-chi1z": "0.8",
    "initial-bh-chi2z": "0.8",
    "relaxed-time": "310.888889000000006",
    "relaxed-mass1": "0.374851674600784",
    "relaxed-mass2": "0.62468360352252",
    "relaxed-total-mass": "0.999535278123304",
    "relaxed-mass-ratio-1-over-2": "0.600066453620742",
    "relaxed-LNhatx": "3.25910780486158e-22",
    "relaxed-LNhaty": "5.13934492096912e-22",
    "relaxed-LNhatz": "1",
    "relaxed-nhatx": "0.980956692178206",
    "relaxed-nhaty": "-0.194226589505124",
    "relaxed-nhatz": "-2.19884617541888e-22",
    "relaxed-chi1z": "0.800657150673698",
    "relaxed-chi2z": "0.800816668335319",
    "final-mass": "0.9184440419",
    "final-chi": "0.9051050696",
    "peak-omega-22": "0.434009578",
    "peak-ampl-22": "0.370324255",
    "peak-luminosity-ergs-per-sec": "5.3698814e+56",
    "final-kick": "9.47"
}