{
    "catalog-tag": "RIT:BBH:0714",
    "resolution-tag": "n120",
    "id-tag": "id1",
    "run-name": "D12.00_q0.2500_a-0.70_0.40_opt2_n120",
    "data-type": "NR",
    "system-type": "Aligned",
    "comments": "none",
    "authors-emails": "JamesHealy<jchsma@rit.edu>,CarlosLousto<colsma@rit.edu>",
    "simulation-bibtex-keys": "",
    "code-bibtex-keys": "Campanelli:2005dd",
    "initial-data-bibtex-keys": "Bowen:1980yu,Brandt:1997tf,Ansorg:2004ds",
    "quasicircular-bibtex-keys": "Husa:2007rh,Buonanno:2010yk,Healy:2017zqj",
    "eccentricity-bibtex-keys": "Campanelli:2008nk",
    "extrapolation-bibtex-keys": "Nakano:2015pta",
    "code": "LazEv",
    "evolution-system": "BSSN",
    "evolution-gauge": "1+log/Gamma-driver(eta=2.0)",
    "cfl": "0.333333333333333",
    "fd-order": "6",
    "dissipation-order": "5",
    "eccentricity-measurement-method": "r^2-rddot",
    "eccentricity": "0.0007192891",
    "freq-start-22": "0.007037123574207",
    "freq-start-22-Hz-1Msun": "1428.352992654946547",
    "number-of-cycles-22": "",
    "number-of-orbits": "16.2696198230103",
    "initial-data-type": "Bowen-Yorkquasicircular",
    "initial-ADM-energy": "0.99437885016617",
    "initial-orbital-angular-momentum": "0.646544931795996",
    "initial-ADM-angular-momentum-x": "0",
    "initial-ADM-angular-momentum-y": "0",
    "initial-ADM-angular-momentum-z": "0.874544931795996",
    "initial-separation": "12",
    "initial-mass1": "0.2",
    "initial-mass2": "0.8",
    "initial-total-mass": "1",
    "initial-bh-chi1z": "-0.7",
    "initial-bh-chi2z": "0.4",
    "relaxed-time": "293.3932889999999816",
    "relaxed-mass1": "0.199990455312458",
    "relaxed-mass2": "0.799989511309598",
    "relaxed-total-mass": "0.999979966622056",
    "relaxed-mass-ratio-1-over-2": "0.249991346742871",
    "relaxed-LNhatx": "2.35235237315359e-18",
    "relaxed-LNhaty": "-4.78612010656943e-19",
    "relaxed-LNhatz": "1",
    "relaxed-nhatx": "0.995773517062676",
    "relaxed-nhaty": "-0.0918428152695005",
    "relaxed-nhatz": "-2.38636727046641e-18",
    "relaxed-chi1z": "-0.700208274243672",
    "relaxed-chi2z": "0.400023509345348",
    "final-mass": "0.9725715979",
    "final-chi": "0.6665799970",
    "peak-omega-22": "0.34719036",
    "peak-ampl-22": "0.239804247",
    "peak-luminosity-ergs-per-sec": "1.6846106e+56",
    "final-kick": "80.54"
}